modules/__init__.py
modules/azorult/__init__.py
modules/azorult/azorult.py
modules/citadel/__init__.py
modules/citadel/citadel.py
mwcfg-1.0.1.data/scripts/mwcfg
mwcfg-1.0.1.dist-info/LICENSE
mwcfg-1.0.1.dist-info/METADATA
mwcfg-1.0.1.dist-info/WHEEL
mwcfg-1.0.1.dist-info/top_level.txt
mwcfg-1.0.1.dist-info/RECORD
