Metadata-Version: 2.1
Name: mwcfg
Version: 1.0.1
Summary: A Modular Malware Configuration Extraction Tool using MalDuck
Home-page: UNKNOWN
Maintainer: c3r3b3ru5
License: UNKNOWN
Platform: UNKNOWN
Classifier: Programming Language :: Python
Classifier: Operating System :: OS Independent
Requires-Dist: malduck (==4.1.0)
Requires-Dist: python-magic (==0.4.22)
